casperfpga/CasperLogHandlers.py
casperfpga/__init__.py
casperfpga/adc.py
casperfpga/async_requester.py
casperfpga/attribute_container.py
casperfpga/bitfield.py
casperfpga/bitsnap.py
casperfpga/casperfpga.py
casperfpga/clockswitch.py
casperfpga/ethernet.py
casperfpga/fortygbe.py
casperfpga/gbe.py
casperfpga/hmc.py
casperfpga/i2c.py
casperfpga/i2c_bar.py
casperfpga/i2c_eeprom.py
casperfpga/i2c_gpio.py
casperfpga/i2c_motion.py
casperfpga/i2c_sn.py
casperfpga/i2c_temp.py
casperfpga/i2c_volt.py
casperfpga/katadc.py
casperfpga/memory.py
casperfpga/network.py
casperfpga/onegbe.py
casperfpga/progska.so
casperfpga/qdr.py
casperfpga/qdr_jack.py
casperfpga/register.py
casperfpga/rmp.py
casperfpga/sbram.py
casperfpga/scroll.py
casperfpga/skarab_definitions.py
casperfpga/skarab_fileops.py
casperfpga/skarabadc.py
casperfpga/snap.py
casperfpga/snapadc.py
casperfpga/spead.py
casperfpga/synth.py
casperfpga/tengbe.py
casperfpga/termcolors.py
casperfpga/transport.py
casperfpga/transport_dummy.py
casperfpga/transport_itpm.py
casperfpga/transport_katcp.py
casperfpga/transport_skarab.py
casperfpga/transport_tapcp.py
casperfpga/utils.py
casperfpga/wishbonedevice.py
casperfpga-0.1.3.data/scripts/casperfpga_deprogram.py
casperfpga-0.1.3.data/scripts/casperfpga_itpm.py
casperfpga-0.1.3.data/scripts/casperfpga_print_snap.py
casperfpga-0.1.3.data/scripts/casperfpga_program.py
casperfpga-0.1.3.data/scripts/casperfpga_tengbe_coreinfo.py
casperfpga-0.1.3.data/scripts/casperfpga_tengbe_snap.py
casperfpga-0.1.3.data/scripts/casperfpga_tengbe_status.py
casperfpga-0.1.3.dist-info/LICENSE.txt
casperfpga-0.1.3.dist-info/METADATA
casperfpga-0.1.3.dist-info/WHEEL
casperfpga-0.1.3.dist-info/top_level.txt
casperfpga-0.1.3.dist-info/RECORD
