Metadata-Version: 2.1
Name: casperfpga
Version: 0.1.3
Summary: Talk to CASPER hardware devices using katcp or dcp. See https://github.com/casper-astro/casperfpga for more.
Home-page: https://github.com/casper-astro/casperfpga
Author: Paul Prozesky
Author-email: apatel@ska.ac.za
License: GNU GPLv2
Download-URL: https://pypi.org/project/casperfpga
Keywords: casper ska meerkat fpga
Platform: UNKNOWN
Classifier: License :: OSI Approved :: GNU General Public License v2 (GPLv2)
Classifier: Programming Language :: Python :: 2.7
Classifier: Operating System :: OS Independent
Classifier: Topic :: Software Development :: Libraries :: Python Modules
Classifier: Topic :: Scientific/Engineering :: Astronomy
Requires-Dist: katcp (==0.6.2)
Requires-Dist: numpy (<1.17)
Requires-Dist: odict
Requires-Dist: setuptools
Requires-Dist: tornado (<5)
